{
  "id": "task_lxhg48m",
  "type": "execution",
  "name": "EXECUTION: Continue your task: Conti",
  "owner": "orchestrator",
  "locked": true,
  "source": "orchestrator",
  "status": "processing",
  "progress": 0,
  "steps": [
    {
      "id": "prepare_tools",
      "label": "Prepare Tools",
      "status": "pending"
    },
    {
      "id": "execute_payload",
      "label": "Execute Payload",
      "status": "pending"
    },
    {
      "id": "verify_output",
      "label": "Verify Output",
      "status": "pending"
    }
  ],
  "logs": [
    {
      "timestamp": "2026-04-14T23:54:36.850Z",
      "level": "info",
      "message": "[SYSTEM] Task \"EXECUTION: Continue your task: Conti\" initialized."
    },
    {
      "timestamp": "2026-04-14T23:54:36.869Z",
      "level": "info",
      "message": "[Reality] Validated platform channels"
    }
  ],
  "created_at": "2026-04-14T23:54:36.850Z",
  "updated_at": "2026-04-14T23:54:36.869Z"
}